[
  {"key": "Abramski2023",   "first_author": "Abramski",    "year": 2023, "cluster": "B", "journal": "Big Data and Cognitive Computing",       "doi": "10.3390/bdcc7030124"},
  {"key": "Abramski2022",   "first_author": "Abramski",    "year": 2022, "cluster": "D", "journal": "Big Data and Cognitive Computing",       "doi": "10.3390/bdcc9070171"},
  {"key": "Haim2025",       "first_author": "Haim",        "year": 2025, "cluster": "B", "journal": "arXiv preprint",                         "doi": "arXiv:2502.19529"},
  {"key": "Almaatouq2022",  "first_author": "Almaatouq",   "year": 2022, "cluster": "C", "journal": "Phil. Trans. Royal Society B",           "doi": "10.1098/rstb.2020.0315"},
  {"key": "Beckage2020",    "first_author": "Beckage",     "year": 2020, "cluster": "A", "journal": "Proc. Royal Society A",                  "doi": "10.1098/rspa.2019.0825"},
  {"key": "BorgeH2010",     "first_author": "Borge-H.",    "year": 2010, "cluster": "D", "journal": "Entropy",                                "doi": "10.3390/e12051264"},
  {"key": "Bullmore2012",   "first_author": "Bullmore",    "year": 2012, "cluster": "A", "journal": "Nature Reviews Neuroscience",            "doi": "10.1038/nrn3214"},
  {"key": "Chen2023",       "first_author": "Chen",        "year": 2023, "cluster": "E", "journal": "Behavior Research Methods",              "doi": "10.3758/s13428-023-02148-6"},
  {"key": "Citraro2023",    "first_author": "Citraro",     "year": 2023, "cluster": "A", "journal": "EPJ Data Science",                       "doi": "10.1140/epjds/s13688-023-00423-4"},
  {"key": "Cole2015",       "first_author": "Cole",        "year": 2015, "cluster": "A", "journal": "Journal of Cognitive Neuroscience",      "doi": "10.1162/jocn_a_00810"},
  {"key": "Colleoni2024",   "first_author": "Colleoni",    "year": 2024, "cluster": "C", "journal": "Patterns",                               "doi": "10.1016/j.patter.2024.101074"},
  {"key": "DeDuro2025",     "first_author": "De Duro",     "year": 2025, "cluster": "B", "journal": "EPJ Data Science",                       "doi": "10.1140/epjds/s13688-025-00600-7"},
  {"key": "Denervaud2021",  "first_author": "Denervaud",   "year": 2021, "cluster": "E", "journal": "npj Science of Learning",                "doi": "10.1038/s41539-021-00113-2"},
  {"key": "Dyer2020",       "first_author": "Dyer",        "year": 2020, "cluster": "D", "journal": "Applied Network Science",                "doi": "10.1007/s41109-020-00334-7"},
  {"key": "Fatima2021",     "first_author": "Fatima",      "year": 2021, "cluster": "D", "journal": "Big Data and Cognitive Computing",       "doi": "10.3390/bdcc5040077"},
  {"key": "Giabbanel2024",  "first_author": "Giabbanelli", "year": 2024, "cluster": "D", "journal": "Springer book chapter",                  "doi": "10.1007/978-3-031-12345-0_11"},
  {"key": "Haim2026",       "first_author": "Haim",        "year": 2026, "cluster": "B", "journal": "Journal of Computational Social Science", "doi": "10.1007/s42001-025-00446-z"},
  {"key": "Kenett2023",     "first_author": "Kenett",      "year": 2023, "cluster": "B", "journal": "Memory & Cognition",                     "doi": "10.3758/s13421-022-01372-9"},
  {"key": "KenettB2024",    "first_author": "Kenett",      "year": 2024, "cluster": "E", "journal": "Psychological Review",                   "doi": "10.1037/rev0000431"},
  {"key": "Liu2024",        "first_author": "Liu",         "year": 2024, "cluster": "D", "journal": "Frontiers in Artificial Intelligence",   "doi": "10.3389/frai.2024.1406773"},
  {"key": "Luchini2024",    "first_author": "Luchini",     "year": 2024, "cluster": "E", "journal": "Journal of Intelligence",                "doi": "10.3390/jintelligence12060056"},
  {"key": "Page2021",       "first_author": "Page",        "year": 2021, "cluster": "A", "journal": "BMJ",                                    "doi": "10.1136/bmj.n71"},
  {"key": "Rahwan2019",     "first_author": "Rahwan",      "year": 2019, "cluster": "C", "journal": "Nature",                                 "doi": "10.1038/s41586-019-1138-y"},
  {"key": "Semeraro2021",   "first_author": "Semeraro",    "year": 2021, "cluster": "B", "journal": "PeerJ Computer Science",                 "doi": "10.7717/peerj-cs.295"},
  {"key": "Semeraro2025",   "first_author": "Semeraro",    "year": 2025, "cluster": "D", "journal": "Journal of Computational Social Science", "doi": "10.1007/s42001-024-00295-6"},
  {"key": "Siew2019",       "first_author": "Siew",        "year": 2019, "cluster": "A", "journal": "Complexity",                             "doi": "10.1155/2019/2108423"},
  {"key": "Siew2019b",      "first_author": "Siew",        "year": 2019, "cluster": "A", "journal": "Brain Sciences",                         "doi": "10.3390/brainsci11121628"},
  {"key": "Stella2020",     "first_author": "Stella",      "year": 2020, "cluster": "D", "journal": "Systems",                                "doi": "10.3390/systems8040038"},
  {"key": "Stella2022",     "first_author": "Stella",      "year": 2022, "cluster": "A", "journal": "Topics in Cognitive Science",            "doi": "10.1111/tops.12551"},
  {"key": "Stella2022b",    "first_author": "Stella",      "year": 2022, "cluster": "D", "journal": "Big Data and Cognitive Computing",       "doi": "10.3390/bdcc6020052"},
  {"key": "Stella2024",     "first_author": "Stella",      "year": 2024, "cluster": "A", "journal": "Psychonomic Bulletin & Review",          "doi": "10.3758/s13423-024-02473-9"},
  {"key": "Stella2026",     "first_author": "Stella",      "year": 2026, "cluster": "A", "journal": "WIREs Cognitive Science",                "doi": "10.1002/wcs.70026"},
  {"key": "StellaVit2019",  "first_author": "Stella",      "year": 2019, "cluster": "A", "journal": "Big Data and Cognitive Computing",       "doi": "10.3390/bdcc3010010"},
  {"key": "Teixeira2021",   "first_author": "Teixeira",    "year": 2021, "cluster": "D", "journal": "Scientific Reports",                     "doi": "10.1038/s41598-021-98147-w"},
  {"key": "Vitevitch2023",  "first_author": "Vitevitch",   "year": 2023, "cluster": "A", "journal": "Brain Sciences",                         "doi": "10.3390/brainsci13020188"},
  {"key": "Vitevitch2024",  "first_author": "Vitevitch",   "year": 2024, "cluster": "A", "journal": "Information",                            "doi": "10.3390/info15070401"}
]
